rolling_window/__init__.py
rolling_window/helpers.py
rolling_window/peristance.py
rolling_window/rolling_window.py
rolling_window/test_rolling_window.py
rolling_window-0.1.2.dist-info/LICENSE
rolling_window-0.1.2.dist-info/METADATA
rolling_window-0.1.2.dist-info/WHEEL
rolling_window-0.1.2.dist-info/top_level.txt
rolling_window-0.1.2.dist-info/RECORD
