Metadata-Version: 2.1
Name: rolling-window
Version: 0.1.2
Summary: UNKNOWN
Home-page: UNKNOWN
License: MIT License
Platform: UNKNOWN
Classifier: Programming Language :: Python :: 3
Requires-Python: >=3.7
Requires-Dist: hickle
Requires-Dist: paco
Requires-Dist: numpy
